skyrl_train/__init__.py
skyrl_train/evaluate.py
skyrl_train/fully_async_trainer.py
skyrl_train/model_wrapper.py
skyrl_train/trainer.py
skyrl_train/training_batch.py
skyrl_train/weights_manager.py
skyrl_train/config/__init__.py
skyrl_train/config/ppo_base_config.yaml
skyrl_train/config/utils.py
skyrl_train/config/deepspeed_config/eval.yaml
skyrl_train/config/deepspeed_config/train.yaml
skyrl_train/config/megatron_config/policy.yaml
skyrl_train/config/megatron_config/ref.yaml
skyrl_train/config/skyrl_gym_config/default.yaml
skyrl_train/dataset/__init__.py
skyrl_train/dataset/dataset.py
skyrl_train/dataset/preprocess.py
skyrl_train/dataset/replay_buffer.py
skyrl_train/distributed/__init__.py
skyrl_train/distributed/deepspeed_strategy.py
skyrl_train/distributed/dispatch.py
skyrl_train/distributed/fsdp_strategy.py
skyrl_train/distributed/fsdp_utils.py
skyrl_train/distributed/strategy.py
skyrl_train/distributed/utils.py
skyrl_train/distributed/megatron/megatron_strategy.py
skyrl_train/distributed/megatron/megatron_utils.py
skyrl_train/distributed/megatron/model_utils.py
skyrl_train/distributed/megatron/optimizer.py
skyrl_train/distributed/ulysses/__init__.py
skyrl_train/distributed/ulysses/monkey_patch.py
skyrl_train/distributed/ulysses/utils.py
skyrl_train/entrypoints/main_base.py
skyrl_train/entrypoints/main_generate.py
skyrl_train/generators/__init__.py
skyrl_train/generators/base.py
skyrl_train/generators/skyrl_gym_generator.py
skyrl_train/generators/utils.py
skyrl_train/inference_engines/__init__.py
skyrl_train/inference_engines/base.py
skyrl_train/inference_engines/inference_engine_client.py
skyrl_train/inference_engines/inference_engine_client_http_endpoint.py
skyrl_train/inference_engines/ray_wrapped_inference_engine.py
skyrl_train/inference_engines/remote_inference_engine.py
skyrl_train/inference_engines/utils.py
skyrl_train/inference_engines/sglang/sglang_engine.py
skyrl_train/inference_engines/sglang/sglang_server.py
skyrl_train/inference_engines/vllm/utils.py
skyrl_train-0.3.0.dist-info/METADATA
skyrl_train-0.3.0.dist-info/WHEEL
skyrl_train-0.3.0.dist-info/top_level.txt
skyrl_train-0.3.0.dist-info/RECORD
