Metadata-Version: 2.4
Name: skyrl-train
Version: 0.3.0
Summary: skyrl-train
Author-email: NovaSkyAI <novasky.berkeley@gmail.com>
License: MIT
Classifier: Programming Language :: Python :: 3
Classifier: License :: OSI Approved :: MIT License
Classifier: Operating System :: OS Independent
Requires-Python: ==3.12.*
Requires-Dist: loguru
Requires-Dist: tqdm
Requires-Dist: ninja
Requires-Dist: tensorboard
Requires-Dist: func_timeout
Requires-Dist: transformers>=4.51.0
Requires-Dist: hydra-core==1.3.2
Requires-Dist: accelerate
Requires-Dist: torchdata
Requires-Dist: omegaconf
Requires-Dist: ray==2.51.1
Requires-Dist: peft
Requires-Dist: debugpy==1.8.0
Requires-Dist: hf_transfer
Requires-Dist: wandb
Requires-Dist: datasets==4.0.0
Requires-Dist: tensordict
Requires-Dist: jaxtyping
Requires-Dist: skyrl-gym
Requires-Dist: flash-attn
Requires-Dist: polars
Requires-Dist: s3fs
Requires-Dist: fastapi
Requires-Dist: uvicorn
Provides-Extra: deepspeed
Requires-Dist: deepspeed==0.17.6; extra == "deepspeed"
Provides-Extra: dev
Requires-Dist: ruff==0.11.9; extra == "dev"
Requires-Dist: black==24.10.0; extra == "dev"
Requires-Dist: pytest>=6.2.5; extra == "dev"
Requires-Dist: pytest-asyncio; extra == "dev"
Requires-Dist: pre-commit; extra == "dev"
Requires-Dist: litellm; extra == "dev"
Provides-Extra: docs
Requires-Dist: sphinx>=7.0.0; extra == "docs"
Requires-Dist: sphinx-rtd-theme>=2.0.0; extra == "docs"
Requires-Dist: sphinx-autodoc-typehints>=1.25.0; extra == "docs"
Requires-Dist: myst-parser>=2.0.0; extra == "docs"
Requires-Dist: sphinx-copybutton>=0.5.0; extra == "docs"
Requires-Dist: sphinx-autobuild>=2021.3.14; extra == "docs"
Provides-Extra: sandboxes
Requires-Dist: litellm[proxy]>=1.67.5; extra == "sandboxes"
Provides-Extra: vllm
Requires-Dist: vllm==0.11.0; extra == "vllm"
Requires-Dist: flash-attn==2.8.3; extra == "vllm"
Requires-Dist: torch==2.8.0; extra == "vllm"
Requires-Dist: flashinfer-python; extra == "vllm"
Requires-Dist: flashinfer-jit-cache; extra == "vllm"
Requires-Dist: torchvision; extra == "vllm"
Provides-Extra: sglang
Requires-Dist: sglang[openai,srt,torch_memory_saver]==0.4.8.post1; extra == "sglang"
Requires-Dist: flashinfer-python; extra == "sglang"
Requires-Dist: flash-attn==2.8.3; extra == "sglang"
Requires-Dist: torch==2.7.1; extra == "sglang"
Requires-Dist: torchvision; extra == "sglang"
Provides-Extra: mcore
Requires-Dist: transformer-engine[pytorch]==2.7.0; extra == "mcore"
Requires-Dist: flash-attn==2.7.4.post1; extra == "mcore"
Requires-Dist: vllm==0.10.1.1; extra == "mcore"
Requires-Dist: torch==2.7.1; extra == "mcore"
Requires-Dist: flashinfer-python; extra == "mcore"
Requires-Dist: torchvision; extra == "mcore"
Requires-Dist: megatron-bridge==0.1.0rc4; extra == "mcore"
Requires-Dist: megatron-core==0.14.0; extra == "mcore"
Provides-Extra: flashrl
Requires-Dist: flash-attn==2.8.3; extra == "flashrl"
Requires-Dist: torch==2.7.0; extra == "flashrl"
Requires-Dist: flashinfer-python; extra == "flashrl"
Requires-Dist: torchvision; extra == "flashrl"
Provides-Extra: miniswe
Requires-Dist: mini-swe-agent>=1.12.0; extra == "miniswe"
Requires-Dist: litellm; extra == "miniswe"
